alamari/__about__.py
alamari/__init__.py
alamari/convert.py
alamari/humanize.py
alamari/utils.py
alamari-0.1.1.dist-info/LICENSE.md
alamari-0.1.1.dist-info/METADATA
alamari-0.1.1.dist-info/WHEEL
alamari-0.1.1.dist-info/top_level.txt
alamari-0.1.1.dist-info/RECORD
