Metadata-Version: 2.1
Name: alamari
Version: 0.1.1
Summary: A collection of utils that you might not require but might need.
Home-page: https://github.com/sidbelbase/alamari
Author: Siddharth Belbase
Author-email: siddharthbelbase@gmail.com
License: MIT
Keywords: nepali-utils,made-in-nepal,nepal,nepali-developer,nepali-package,pluralize,devanagari,roman,nepal-time,helper-functions,utilities
Platform: UNKNOWN
Classifier: Programming Language :: Python :: 3
Classifier: License :: OSI Approved :: MIT License
Classifier: Operating System :: OS Independent
Requires-Python: >=3.6
Requires-Dist: arrow
Requires-Dist: nepali-datetime
Requires-Dist: nepali-roman
Requires-Dist: python-dateutil
Requires-Dist: requests
